LICENSE
README.md
setup.cfg
setup.py
TunAugmentor/__init__.py
TunAugmentor/logger.py
TunAugmentor/pipeline.py
TunAugmentor/utils.py
TunAugmentor.egg-info/PKG-INFO
TunAugmentor.egg-info/SOURCES.txt
TunAugmentor.egg-info/dependency_links.txt
TunAugmentor.egg-info/requires.txt
TunAugmentor.egg-info/top_level.txt
TunAugmentor/transformations/__init__.py
TunAugmentor/transformations/basic_transform.py
TunAugmentor/transformations/crops.py
TunAugmentor/transformations/flips.py
TunAugmentor/transformations/pixel_transformations.py
TunAugmentor/transformations/rotations.py
TunAugmentor/transformations/translations.py
TunAugmentor/transformations/zoom.py
tests/__init__.py
tests/test_transformations.py